aioradios/__init__.py
aioradios/base_url.py
aioradios/client.py
aioradios/errors.py
aioradios/http.py
aioradios-0.2.6.dist-info/LICENCE
aioradios-0.2.6.dist-info/METADATA
aioradios-0.2.6.dist-info/WHEEL
aioradios-0.2.6.dist-info/top_level.txt
aioradios-0.2.6.dist-info/RECORD
