Metadata-Version: 2.1
Name: aioradios
Version: 0.2.6
Summary: An asynchronous API wrapper for www.radio-browser.info
Home-page: https://github.com/P3qch/aioradios
Author: Peach
Author-email: ariechertkov@gmail.com
License: UNKNOWN
Platform: UNKNOWN
Classifier: Programming Language :: Python :: 3
Classifier: License :: OSI Approved :: MIT License
Classifier: Operating System :: OS Independent
Requires-Python: >=3.5
Requires-Dist: aiodns
Requires-Dist: aiohttp
